{
  "$schema": "https://developer.microsoft.com/json-schemas/spfx-build/package-solution.schema.json",
  "solution": {
    "name": "spfx-api-example-client-side-solution",
    "id": "d0f8b53e-9e90-4a59-b2e6-db3ae054f125",
    "version": "1.0.0.0",
    "includeClientSideAssets": true,
    "skipFeatureDeployment": true,
    "isDomainIsolated": false,
    "developer": {
      "name": "",
      "websiteUrl": "",
      "privacyUrl": "",
      "termsOfUseUrl": "",
      "mpnId": "Undefined-1.20.0"
    },
    "metadata": {
      "shortDescription": {
        "default": "spfx-api-example description"
      },
      "longDescription": {
        "default": "spfx-api-example description"
      },
      "screenshotPaths": [],
      "videoUrl": "",
      "categories": []
    },
    "features": [
      {
        "title": "spfx-api-example Feature",
        "description": "The feature that activates elements of the spfx-api-example solution.",
        "id": "13f340a3-7cea-4f4c-8aaf-21c5f350e4b1",
        "version": "1.0.0.0"
      }
    ],
    "webApiPermissionRequests": [
      {
        "resource": "Microsoft Graph",
        "scope": "User.ReadBasic.All"
      }
    ]
  },
  "paths": {
    "zippedPackage": "solution/spfx-api-example.sppkg"
  }
}
